{
    "rest_id": "1587792361072967680",
    "like_count": 10,
    "quote_count": 0,
    "reply_count": 0,
    "retweet_count": 0,
    "bookmark_count": 0,
    "content": "@officialavatar So Beautiful \ud83d\ude22",
    "hashtags": []
},
{
    "rest_id": "1587807822267359238",
    "like_count": 0,
    "quote_count": 0,
    "reply_count": 1,
    "retweet_count": 0,
    "bookmark_count": 0,
    "content": "@officialavatar Screenshot this @pikaso_me",
    "hashtags": []
},
{
    "rest_id": "1587784287486898176",
    "like_count": 1,
    "quote_count": 0,
    "reply_count": 0,
    "retweet_count": 0,
    "bookmark_count": 0,
    "content": "@officialavatar Emanna timing ha ...\ud83d\udd25\ud83d\udc4c",
    "hashtags": []
},
{
    "rest_id": "1587783681535770625",
    "like_count": 1,
    "quote_count": 0,
    "reply_count": 0,
    "retweet_count": 0,
    "bookmark_count": 0,
    "content": "@officialavatar @JimCameron  \ud83d\udd25\ud83d\udd25\ud83d\udd25\ud83d\udd25\ud83d\udd25\ud83d\udd25\ud83d\udd25",
    "hashtags": []
},
{
    "rest_id": "1587783194408910848",
    "like_count": 0,
    "quote_count": 0,
    "reply_count": 0,
    "retweet_count": 0,
    "bookmark_count": 0,
    "content": "@officialavatar Pog can't wait !",
    "hashtags": []
},
{
    "rest_id": "1587786267663777792",
    "like_count": 2,
    "quote_count": 0,
    "reply_count": 0,
    "retweet_count": 0,
    "bookmark_count": 0,
    "content": "@officialavatar LO'AK AND TSIREYA I KNEW!!!!! I'M ALREADY LOVING",
    "hashtags": []
},
{
    "rest_id": "1587784046687436806",
    "like_count": 53,
    "quote_count": 0,
    "reply_count": 0,
    "retweet_count": 3,
    "bookmark_count": 0,
    "content": "@officialavatar Screaming https://t.co/jV4KDje5S3",
    "hashtags": []
},
{
    "rest_id": "1587781766844219394",
    "like_count": 9,
    "quote_count": 0,
    "reply_count": 0,
    "retweet_count": 0,
    "bookmark_count": 0,
    "content": "@officialavatar i have been waiting for this movie since the last one..i couldnt be happier",
    "hashtags": []
},
{
    "rest_id": "1587983951095660545",
    "like_count": 0,
    "quote_count": 0,
    "reply_count": 0,
    "retweet_count": 0,
    "bookmark_count": 0,
    "content": "@officialavatar Same shit in water instead of forest",
    "hashtags": []
},
{
    "rest_id": "1589710593195331584",
    "like_count": 0,
    "quote_count": 0,
    "reply_count": 0,
    "retweet_count": 0,
    "bookmark_count": 0,
    "content": "@officialavatar I watched Avatar again this weekend thinking that was 2009 technology and my 2021 TV that it was going to look not so great. Man was I wrong. I just had the HD version because Cameron won\u2019t release 4K!!!! yet. But it was still a very very good movie. I can\u2019t wait for the new one",
    "hashtags": []
},
{
    "rest_id": "1587782665570496513",
    "like_count": 0,
    "quote_count": 0,
    "reply_count": 0,
    "retweet_count": 0,
    "bookmark_count": 0,
    "content": "@officialavatar Yt lo Upload chei ra Sunta.",
    "hashtags": []
},
{
    "rest_id": "1587783617505173506",
    "like_count": 0,
    "quote_count": 0,
    "reply_count": 0,
    "retweet_count": 0,
    "bookmark_count": 0,
    "content": "@officialavatar Anthem lede",
    "hashtags": []
},
{
    "rest_id": "1587784385318686720",
    "like_count": 1,
    "quote_count": 0,
    "reply_count": 0,
    "retweet_count": 0,
    "bookmark_count": 0,
    "content": "@officialavatar \ud83d\udd25\ud83d\udd25",
    "hashtags": []
},
{
    "rest_id": "1587815979085611010",
    "like_count": 1,
    "quote_count": 0,
    "reply_count": 0,
    "retweet_count": 0,
    "bookmark_count": 0,
    "content": "@officialavatar https://t.co/ODVg2FkbCF",
    "hashtags": []
},
{
    "rest_id": "1587782145686536193",
    "like_count": 0,
    "quote_count": 0,
    "reply_count": 0,
    "retweet_count": 0,
    "bookmark_count": 0,
    "content": "@officialavatar super",
    "hashtags": []
},
{
    "rest_id": "1587785317444108293",
    "like_count": 565,
    "quote_count": 0,
    "reply_count": 2,
    "retweet_count": 13,
    "bookmark_count": 3,
    "content": "@officialavatar https://t.co/rtNoVQyJ86",
    "hashtags": []
},
{
    "rest_id": "1588660915947593728",
    "like_count": 0,
    "quote_count": 0,
    "reply_count": 0,
    "retweet_count": 0,
    "bookmark_count": 0,
    "content": "@officialavatar @avatartwotoken $AVATAR #AVATAR2 #CRYPTO #ETH #GEMS #VITALIK #ELON \n\nCA: 0x8198f65f8c75beaa7030f194bdf7850f72082afa\n\nhttps://t.co/iPa53wN5nW",
    "hashtags": [
        {
            "indices": [
                40,
                48
            ],
            "text": "AVATAR2"
        },
        {
            "indices": [
                49,
                56
            ],
            "text": "CRYPTO"
        },
        {
            "indices": [
                57,
                61
            ],
            "text": "ETH"
        },
        {
            "indices": [
                62,
                67
            ],
            "text": "GEMS"
        },
        {
            "indices": [
                68,
                76
            ],
            "text": "VITALIK"
        },
        {
            "indices": [
                77,
                82
            ],
            "text": "ELON"
        }
    ]
},
{
    "rest_id": "1587781981106208771",
    "like_count": 1,
    "quote_count": 0,
    "reply_count": 0,
    "retweet_count": 0,
    "bookmark_count": 0,
    "content": "@officialavatar After winning #India \ud83c\uddee\ud83c\uddf3",
    "hashtags": [
        {
            "indices": [
                30,
                36
            ],
            "text": "India"
        }
    ]
},
{
    "rest_id": "1587782284463292417",
    "like_count": 576,
    "quote_count": 2,
    "reply_count": 3,
    "retweet_count": 32,
    "bookmark_count": 4,
    "content": "@officialavatar IM SO HAPPYYYYYY https://t.co/BEFkJxICKS",
    "hashtags": []
},
{
    "rest_id": "1587782765360992256",
    "like_count": 0,
    "quote_count": 0,
    "reply_count": 0,
    "retweet_count": 0,
    "bookmark_count": 0,
    "content": "@officialavatar #AvatarTheWayOfWater #Avatar #Avatar2Trailer #Avatar2 #Salaar #Prabhas",
    "hashtags": [
        {
            "indices": [
                16,
                36
            ],
            "text": "AvatarTheWayOfWater"
        },
        {
            "indices": [
                37,
                44
            ],
            "text": "Avatar"
        },
        {
            "indices": [
                45,
                60
            ],
            "text": "Avatar2Trailer"
        },
        {
            "indices": [
                61,
                69
            ],
            "text": "Avatar2"
        },
        {
            "indices": [
                70,
                77
            ],
            "text": "Salaar"
        },
        {
            "indices": [
                78,
                86
            ],
            "text": "Prabhas"
        }
    ]
},
{
    "rest_id": "1587861768621420547",
    "like_count": 0,
    "quote_count": 0,
    "reply_count": 1,
    "retweet_count": 0,
    "bookmark_count": 0,
    "content": "@officialavatar This movie needs to partner with VR makers for home release.\n\nPSVR2, Meta Quest 2 or Pro, and the like will be the best place to experience this!",
    "hashtags": []
},
{
    "rest_id": "1587784279983013890",
    "like_count": 1,
    "quote_count": 0,
    "reply_count": 0,
    "retweet_count": 0,
    "bookmark_count": 0,
    "content": "@officialavatar I can't quite believe it's finally coming but my god it looks amazing. \ud83c\udf0f\ud83d\udc0b\ud83d\udc99",
    "hashtags": []
},
{
    "rest_id": "1587783711097245703",
    "like_count": 0,
    "quote_count": 0,
    "reply_count": 2,
    "retweet_count": 0,
    "bookmark_count": 0,
    "content": "@officialavatar Can anyone say on which YouTube channel I can watch",
    "hashtags": []
},
{
    "rest_id": "1587783811236261888",
    "like_count": 0,
    "quote_count": 0,
    "reply_count": 0,
    "retweet_count": 0,
    "bookmark_count": 0,
    "content": "@officialavatar Ramppp \ud83d\udca5\ud83d\udca5\ud83d\udca5",
    "hashtags": []
},
{
    "rest_id": "1587781895810875393",
    "like_count": 4,
    "quote_count": 0,
    "reply_count": 0,
    "retweet_count": 0,
    "bookmark_count": 1,
    "content": "@officialavatar Time sense leda ra unga\ud83e\udd72 https://t.co/9HYVQzfbEW",
    "hashtags": []
},
{
    "rest_id": "1587784647395930117",
    "like_count": 2,
    "quote_count": 0,
    "reply_count": 0,
    "retweet_count": 0,
    "bookmark_count": 0,
    "content": "@officialavatar The EPIC is back\ud83d\udc99",
    "hashtags": []
},
{
    "rest_id": "1587785153396363264",
    "like_count": 1,
    "quote_count": 0,
    "reply_count": 0,
    "retweet_count": 0,
    "bookmark_count": 0,
    "content": "@officialavatar Get ready \ud83d\ude02 @Diluc333Za",
    "hashtags": []
},
{
    "rest_id": "1587782741331828736",
    "like_count": 1,
    "quote_count": 0,
    "reply_count": 1,
    "retweet_count": 0,
    "bookmark_count": 0,
    "content": "@officialavatar @vkey_talks here you go",
    "hashtags": []
},
{
    "rest_id": "1587782427589726222",
    "like_count": 0,
    "quote_count": 0,
    "reply_count": 0,
    "retweet_count": 0,
    "bookmark_count": 0,
    "content": "@officialavatar \u2728\ud83d\udca7\u2764\ufe0f",
    "hashtags": []
},
{
    "rest_id": "1587783328207634432",
    "like_count": 0,
    "quote_count": 0,
    "reply_count": 0,
    "retweet_count": 0,
    "bookmark_count": 0,
    "content": "@officialavatar And it's here #AvatarTheWayOfWater",
    "hashtags": [
        {
            "indices": [
                30,
                50
            ],
            "text": "AvatarTheWayOfWater"
        }
    ]
},
{
    "rest_id": "1587782816355741698",
    "like_count": 0,
    "quote_count": 0,
    "reply_count": 0,
    "retweet_count": 0,
    "bookmark_count": 0,
    "content": "@officialavatar Waterr\ud83c\udf0a\ud83c\udf0a",
    "hashtags": []
},
{
    "rest_id": "1587784312652722178",
    "like_count": 0,
    "quote_count": 0,
    "reply_count": 0,
    "retweet_count": 0,
    "bookmark_count": 0,
    "content": "@officialavatar YouTube lo petti dhobbichukko",
    "hashtags": []
},
{
    "rest_id": "1588136408518107136",
    "like_count": 0,
    "quote_count": 0,
    "reply_count": 0,
    "retweet_count": 0,
    "bookmark_count": 0,
    "content": "@officialavatar #UFC Bantamweight Grand Prix for an interim champ while Aljo is on \"vacation\":\n\nSean O'Malley vs Marlon Vera 2\nMerab Dvalishvili vs Henry Cejudo\n#MMA #MMATwitter https://t.co/BlcTG3EQQ2",
    "hashtags": [
        {
            "indices": [
                16,
                20
            ],
            "text": "UFC"
        },
        {
            "indices": [
                161,
                165
            ],
            "text": "MMA"
        },
        {
            "indices": [
                166,
                177
            ],
            "text": "MMATwitter"
        }
    ]
},
{
    "rest_id": "1587783385736519680",
    "like_count": 0,
    "quote_count": 0,
    "reply_count": 0,
    "retweet_count": 0,
    "bookmark_count": 0,
    "content": "@officialavatar Amazing visuals for what will be a simple plot.",
    "hashtags": []
},
{
    "rest_id": "1587782462137978880",
    "like_count": 0,
    "quote_count": 0,
    "reply_count": 0,
    "retweet_count": 0,
    "bookmark_count": 0,
    "content": "@officialavatar @KicchhaCult Damn finally !!!!!!",
    "hashtags": []
},
{
    "rest_id": "1587782224233070592",
    "like_count": 0,
    "quote_count": 0,
    "reply_count": 0,
    "retweet_count": 0,
    "bookmark_count": 0,
    "content": "@officialavatar IM CRYIGN",
    "hashtags": []
},
{
    "rest_id": "1587788151065817089",
    "like_count": 10,
    "quote_count": 0,
    "reply_count": 0,
    "retweet_count": 1,
    "bookmark_count": 1,
    "content": "@officialavatar \ud83d\ude4f\ud83d\udc4f https://t.co/fP1yT4LR6I",
    "hashtags": []
},
{
    "rest_id": "1587795663856668673",
    "like_count": 1,
    "quote_count": 0,
    "reply_count": 1,
    "retweet_count": 0,
    "bookmark_count": 0,
    "content": "@officialavatar @Cornelius_1st",
    "hashtags": []
},
{
    "rest_id": "1587784022792765440",
    "like_count": 1,
    "quote_count": 0,
    "reply_count": 0,
    "retweet_count": 0,
    "bookmark_count": 0,
    "content": "@officialavatar Nothing impressive except CGI",
    "hashtags": []
},
{
    "rest_id": "1587816768310894593",
    "like_count": 2,
    "quote_count": 0,
    "reply_count": 0,
    "retweet_count": 0,
    "bookmark_count": 0,
    "content": "@officialavatar This gonna be so fire. The better avatar let\u2019s be real\u2026\ud83d\ude2c",
    "hashtags": []
},
{
    "rest_id": "1587789129806487553",
    "like_count": 1,
    "quote_count": 0,
    "reply_count": 1,
    "retweet_count": 0,
    "bookmark_count": 0,
    "content": "@officialavatar Story is basic just like marvel and Dc buddy really think he be doing special shit",
    "hashtags": []
},
{
    "rest_id": "1587784080187588608",
    "like_count": 0,
    "quote_count": 0,
    "reply_count": 0,
    "retweet_count": 0,
    "bookmark_count": 0,
    "content": "@officialavatar Match ayevaraku wait chesava",
    "hashtags": []
},
{
    "rest_id": "1587782883145666561",
    "like_count": 6,
    "quote_count": 0,
    "reply_count": 0,
    "retweet_count": 0,
    "bookmark_count": 0,
    "content": "@officialavatar I really didn\u2019t want another trailer but damn this looks beautiful. Now show the trailer at IMAX 3D showings of Black Panther 2 like what happened with the first trailer and Doctor Strange 2",
    "hashtags": []
},
{
    "rest_id": "1587783171717857280",
    "like_count": 11,
    "quote_count": 0,
    "reply_count": 1,
    "retweet_count": 0,
    "bookmark_count": 0,
    "content": "@officialavatar AAA ME CORRO",
    "hashtags": []
},
{
    "rest_id": "1587783500631257088",
    "like_count": 0,
    "quote_count": 0,
    "reply_count": 0,
    "retweet_count": 0,
    "bookmark_count": 0,
    "content": "@officialavatar Oh my.. https://t.co/SFu0hCml9B",
    "hashtags": []
},
{
    "rest_id": "1587783160909234176",
    "like_count": 1,
    "quote_count": 0,
    "reply_count": 0,
    "retweet_count": 0,
    "bookmark_count": 1,
    "content": "@officialavatar https://t.co/KRAQHBE1b3",
    "hashtags": []
},
{
    "rest_id": "1587788047709765632",
    "like_count": 5,
    "quote_count": 0,
    "reply_count": 0,
    "retweet_count": 0,
    "bookmark_count": 0,
    "content": "@officialavatar Madly waiting for this masterpiece \ud83d\udc99\n\nThis is going to be huge \ud83d\udd25\ud83d\udd25\u2764\ufe0f\u200d\ud83d\udd25",
    "hashtags": []
},
{
    "rest_id": "1587784196889935872",
    "like_count": 0,
    "quote_count": 0,
    "reply_count": 0,
    "retweet_count": 0,
    "bookmark_count": 0,
    "content": "@officialavatar Thanks next part trailer ki time announce cheyi",
    "hashtags": []
},
{
    "rest_id": "1587782736097738753",
    "like_count": 3,
    "quote_count": 0,
    "reply_count": 0,
    "retweet_count": 0,
    "bookmark_count": 0,
    "content": "@officialavatar Tamil Language Trailer?",
    "hashtags": []
},
{
    "rest_id": "1587825645907857409",
    "like_count": 0,
    "quote_count": 0,
    "reply_count": 0,
    "retweet_count": 0,
    "bookmark_count": 0,
    "content": "@officialavatar Expensive c\u00f3mic movie",
    "hashtags": []
},
{
    "rest_id": "1587782656317685762",
    "like_count": 21,
    "quote_count": 2,
    "reply_count": 15,
    "retweet_count": 0,
    "bookmark_count": 0,
    "content": "@officialavatar What\u2019s the main characters name again?",
    "hashtags": []
},
{
    "rest_id": "1587781805402632192",
    "like_count": 0,
    "quote_count": 0,
    "reply_count": 0,
    "retweet_count": 0,
    "bookmark_count": 0,
    "content": "@officialavatar All the best \ud83e\udd73",
    "hashtags": []
},
{
    "rest_id": "1587786299628404736",
    "like_count": 1,
    "quote_count": 0,
    "reply_count": 0,
    "retweet_count": 0,
    "bookmark_count": 0,
    "content": "@officialavatar Experience the woww\ud83e\udd79\ud83d\ude0d\ud83d\ude0d\ud83d\ude0d\u2764\ufe0f\u2764\ufe0f\u2764\ufe0f",
    "hashtags": []
},
{
    "rest_id": "1588215294266425346",
    "like_count": 1,
    "quote_count": 0,
    "reply_count": 0,
    "retweet_count": 0,
    "bookmark_count": 0,
    "content": "@officialavatar sorry i only know of one avatar, the real one https://t.co/V1fDeRwB0n",
    "hashtags": []
},
{
    "rest_id": "1587787132889800704",
    "like_count": 4,
    "quote_count": 0,
    "reply_count": 0,
    "retweet_count": 0,
    "bookmark_count": 0,
    "content": "@officialavatar Marvel ni lepi denguthunnam \ud83d\udca5\ud83d\udca5",
    "hashtags": []
},
{
    "rest_id": "1587782859313778690",
    "like_count": 0,
    "quote_count": 0,
    "reply_count": 0,
    "retweet_count": 0,
    "bookmark_count": 0,
    "content": "@officialavatar \ud83e\udd75\ud83d\udd25 MindBlowing",
    "hashtags": []
},
{
    "rest_id": "1587783365465292800",
    "like_count": 0,
    "quote_count": 0,
    "reply_count": 0,
    "retweet_count": 0,
    "bookmark_count": 0,
    "content": "@officialavatar rtc x roads lo 1 crore kotinappudu chuddam",
    "hashtags": []
},
{
    "rest_id": "1587783552417923074",
    "like_count": 0,
    "quote_count": 0,
    "reply_count": 0,
    "retweet_count": 0,
    "bookmark_count": 0,
    "content": "@officialavatar Waiting Mama..\ud83c\udf0a #AvatarTheWayOfWater",
    "hashtags": [
        {
            "indices": [
                32,
                52
            ],
            "text": "AvatarTheWayOfWater"
        }
    ]
},
{
    "rest_id": "1587783696941187072",
    "like_count": 0,
    "quote_count": 0,
    "reply_count": 0,
    "retweet_count": 0,
    "bookmark_count": 0,
    "content": "@officialavatar It's been to long! Can't wait",
    "hashtags": []
},
{
    "rest_id": "1587794807644360705",
    "like_count": 70,
    "quote_count": 2,
    "reply_count": 29,
    "retweet_count": 5,
    "bookmark_count": 1,
    "content": "@officialavatar Are these the cgi that supposed to be \"mind blowing\" or \"game changer\"? This is just bad https://t.co/NXhRcgJcBL",
    "hashtags": []
},
{
    "rest_id": "1587782530911961088",
    "like_count": 3,
    "quote_count": 0,
    "reply_count": 2,
    "retweet_count": 0,
    "bookmark_count": 0,
    "content": "@officialavatar Batman's foot \ud83e\uddb6\ud83c\udffb&gt;&gt;&gt;&gt;&gt;&gt;&gt;&gt;&gt; Avatar\n#AvatarTheWayOfWater \n#Batman https://t.co/MwSh1yehI5",
    "hashtags": [
        {
            "indices": [
                76,
                96
            ],
            "text": "AvatarTheWayOfWater"
        },
        {
            "indices": [
                98,
                105
            ],
            "text": "Batman"
        }
    ]
},
{
    "rest_id": "1587786818333937666",
    "like_count": 1,
    "quote_count": 0,
    "reply_count": 0,
    "retweet_count": 0,
    "bookmark_count": 0,
    "content": "@officialavatar avatar more like \ud83d\ude34\ud83d\ude34\ud83d\ude34",
    "hashtags": []
},
{
    "rest_id": "1587782719517298688",
    "like_count": 0,
    "quote_count": 0,
    "reply_count": 0,
    "retweet_count": 0,
    "bookmark_count": 0,
    "content": "@officialavatar \ud83d\udd25",
    "hashtags": []
},
{
    "rest_id": "1587785405553729536",
    "like_count": 2,
    "quote_count": 0,
    "reply_count": 1,
    "retweet_count": 1,
    "bookmark_count": 0,
    "content": "@officialavatar @saithalasuresh",
    "hashtags": []
},
{
    "rest_id": "1587784244960575490",
    "like_count": 0,
    "quote_count": 0,
    "reply_count": 0,
    "retweet_count": 0,
    "bookmark_count": 0,
    "content": "@officialavatar Spectacular one  and the visuals \ud83d\uded0\ud83d\udca5\n\nDefinitely Not going to miss it on FDFS \ud83e\udd75\ud83d\udca5\n\n#AvatarTheWayOfTheWater #AvatarTrailer",
    "hashtags": [
        {
            "indices": [
                97,
                120
            ],
            "text": "AvatarTheWayOfTheWater"
        },
        {
            "indices": [
                121,
                135
            ],
            "text": "AvatarTrailer"
        }
    ]
},
{
    "rest_id": "1587783233533517825",
    "like_count": 37,
    "quote_count": 0,
    "reply_count": 0,
    "retweet_count": 0,
    "bookmark_count": 0,
    "content": "@officialavatar This looks so good! Can't wait! https://t.co/Qdz3FGK4eh",
    "hashtags": []
},
{
    "rest_id": "1587783566427054081",
    "like_count": 0,
    "quote_count": 0,
    "reply_count": 0,
    "retweet_count": 0,
    "bookmark_count": 0,
    "content": "@officialavatar Yes finally",
    "hashtags": []
},
{
    "rest_id": "1587792056008990720",
    "like_count": 4,
    "quote_count": 0,
    "reply_count": 0,
    "retweet_count": 2,
    "bookmark_count": 0,
    "content": "@officialavatar We want #Kannada version\n#Avatar2InKannada",
    "hashtags": [
        {
            "indices": [
                24,
                32
            ],
            "text": "Kannada"
        },
        {
            "indices": [
                41,
                58
            ],
            "text": "Avatar2InKannada"
        }
    ]
},
{
    "rest_id": "1587783928425091072",
    "like_count": 0,
    "quote_count": 0,
    "reply_count": 0,
    "retweet_count": 0,
    "bookmark_count": 0,
    "content": "@officialavatar Masss \ud83e\udd73\ud83e\udd73\ud83e\udd73\ud83d\udd25\ud83d\udd25\ud83d\udd25\ud83d\udd25",
    "hashtags": []
},
{
    "rest_id": "1587782387081121794",
    "like_count": 0,
    "quote_count": 0,
    "reply_count": 0,
    "retweet_count": 0,
    "bookmark_count": 0,
    "content": "@officialavatar O M G",
    "hashtags": []
},
{
    "rest_id": "1587902690960572419",
    "like_count": 0,
    "quote_count": 0,
    "reply_count": 0,
    "retweet_count": 0,
    "bookmark_count": 0,
    "content": "@officialavatar \u2728",
    "hashtags": []
},
{
    "rest_id": "1587785594775683078",
    "like_count": 47,
    "quote_count": 1,
    "reply_count": 14,
    "retweet_count": 1,
    "bookmark_count": 0,
    "content": "@officialavatar Meh. I need something that isn't style over substance, which is the issue with the 1st movie. It may look nice, but a good story makes something timeless and better when you haven't got 3D Imax theatre experience to fall back on at home.",
    "hashtags": []
},
{
    "rest_id": "1587783288781168644",
    "like_count": 5,
    "quote_count": 0,
    "reply_count": 0,
    "retweet_count": 4,
    "bookmark_count": 0,
    "content": "@officialavatar #saaho\n#Pathaan \n#AvatarTheWayOfWater",
    "hashtags": [
        {
            "indices": [
                16,
                22
            ],
            "text": "saaho"
        },
        {
            "indices": [
                23,
                31
            ],
            "text": "Pathaan"
        },
        {
            "indices": [
                33,
                53
            ],
            "text": "AvatarTheWayOfWater"
        }
    ]
},
{
    "rest_id": "1587784894444457987",
    "like_count": 1,
    "quote_count": 0,
    "reply_count": 0,
    "retweet_count": 0,
    "bookmark_count": 0,
    "content": "@officialavatar FUCK this looks so good",
    "hashtags": []
},
{
    "rest_id": "1587784210630463489",
    "like_count": 1,
    "quote_count": 0,
    "reply_count": 0,
    "retweet_count": 0,
    "bookmark_count": 0,
    "content": "@officialavatar Eeyyy Deenthalli \ud83d\udd25\ud83d\udd25\ud83d\udd25\nTHIS IS CINEMA",
    "hashtags": []
},
{
    "rest_id": "1587783063018549254",
    "like_count": 1,
    "quote_count": 0,
    "reply_count": 0,
    "retweet_count": 0,
    "bookmark_count": 0,
    "content": "@officialavatar \ud83d\ude0d",
    "hashtags": []
},
{
    "rest_id": "1588497659618549760",
    "like_count": 0,
    "quote_count": 0,
    "reply_count": 0,
    "retweet_count": 0,
    "bookmark_count": 0,
    "content": "@officialavatar The brilliant Director who gave us the awesome Terminator II stunning special effects is back with more awesome special effects breakthroughs",
    "hashtags": []
},
{
    "rest_id": "1587784079877234688",
    "like_count": 0,
    "quote_count": 0,
    "reply_count": 0,
    "retweet_count": 0,
    "bookmark_count": 0,
    "content": "@officialavatar \ud83d\ude3b\u2764\ufe0f\u200d\ud83d\udd25\ud83d\udd25\ud83e\udd75",
    "hashtags": []
},
{
    "rest_id": "1587783375300984835",
    "like_count": 0,
    "quote_count": 0,
    "reply_count": 0,
    "retweet_count": 0,
    "bookmark_count": 0,
    "content": "@officialavatar When the real world is this unpleasant, get me back to Pandora. Pronto.",
    "hashtags": []
},
{
    "rest_id": "1587877739490689028",
    "like_count": 47,
    "quote_count": 1,
    "reply_count": 1,
    "retweet_count": 5,
    "bookmark_count": 1,
    "content": "@officialavatar We can't wait to dive back in! \ud83c\udf0a",
    "hashtags": []
},
{
    "rest_id": "1587784583625547778",
    "like_count": 3,
    "quote_count": 0,
    "reply_count": 0,
    "retweet_count": 0,
    "bookmark_count": 0,
    "content": "@officialavatar My heart was not ready for all of this epicness and emotion. \ud83d\ude0d",
    "hashtags": []
},
{
    "rest_id": "1587784344353275905",
    "like_count": 0,
    "quote_count": 0,
    "reply_count": 0,
    "retweet_count": 0,
    "bookmark_count": 0,
    "content": "@officialavatar Cameron thatha rocks",
    "hashtags": []
},
{
    "rest_id": "1587781637307260930",
    "like_count": 50,
    "quote_count": 0,
    "reply_count": 2,
    "retweet_count": 0,
    "bookmark_count": 0,
    "content": "@officialavatar DAY ONE! I\u2019ve waited 13 years\ud83d\ude0d",
    "hashtags": []
},
{
    "rest_id": "1587782423244582912",
    "like_count": 0,
    "quote_count": 0,
    "reply_count": 0,
    "retweet_count": 0,
    "bookmark_count": 0,
    "content": "@officialavatar Poonakale theatre lo\ud83d\udd25\ud83d\udd25",
    "hashtags": []
},
{
    "rest_id": "1587814508231286784",
    "like_count": 4,
    "quote_count": 0,
    "reply_count": 0,
    "retweet_count": 0,
    "bookmark_count": 0,
    "content": "@officialavatar BOOOF https://t.co/YmUj4q4hgm",
    "hashtags": []
},
{
    "rest_id": "1587792090964131840",
    "like_count": 2,
    "quote_count": 0,
    "reply_count": 0,
    "retweet_count": 0,
    "bookmark_count": 0,
    "content": "@officialavatar My current students weren\u2019t even born when the first Avatar came out! \ud83e\udd2f",
    "hashtags": []
},
{
    "rest_id": "1587784319942418432",
    "like_count": 0,
    "quote_count": 0,
    "reply_count": 0,
    "retweet_count": 0,
    "bookmark_count": 0,
    "content": "@officialavatar @MahaanISM_ 3 Billion loading",
    "hashtags": []
},
{
    "rest_id": "1587800190664478720",
    "like_count": 4,
    "quote_count": 0,
    "reply_count": 0,
    "retweet_count": 0,
    "bookmark_count": 0,
    "content": "@officialavatar Em chestavo telidu ra\nJathini den***gali \nSare na?\n\nAvatar records ni malli nuvvey lepali",
    "hashtags": []
},
{
    "rest_id": "1587785269109223424",
    "like_count": 16,
    "quote_count": 0,
    "reply_count": 1,
    "retweet_count": 0,
    "bookmark_count": 0,
    "content": "@officialavatar \ud83d\udca5\ud83e\udd75\ud83e\udd19 blast waiting for movie",
    "hashtags": []
},
{
    "rest_id": "1587782882961117186",
    "like_count": 4,
    "quote_count": 0,
    "reply_count": 0,
    "retweet_count": 0,
    "bookmark_count": 1,
    "content": "@officialavatar https://t.co/fZzp9WuzkN",
    "hashtags": []
},
{
    "rest_id": "1587782731228131329",
    "like_count": 0,
    "quote_count": 0,
    "reply_count": 0,
    "retweet_count": 0,
    "bookmark_count": 0,
    "content": "@officialavatar #ThunivuPongal",
    "hashtags": [
        {
            "indices": [
                16,
                30
            ],
            "text": "ThunivuPongal"
        }
    ]
},
{
    "rest_id": "1587782403707265024",
    "like_count": 0,
    "quote_count": 0,
    "reply_count": 0,
    "retweet_count": 0,
    "bookmark_count": 0,
    "content": "@officialavatar I\u2019m crying\ud83d\ude2d",
    "hashtags": []
},
{
    "rest_id": "1587800167822016512",
    "like_count": 2,
    "quote_count": 0,
    "reply_count": 0,
    "retweet_count": 0,
    "bookmark_count": 0,
    "content": "@officialavatar lets go",
    "hashtags": []
},
{
    "rest_id": "1587783404854059012",
    "like_count": 3,
    "quote_count": 1,
    "reply_count": 0,
    "retweet_count": 0,
    "bookmark_count": 0,
    "content": "@officialavatar https://t.co/QWBVdpGq8L",
    "hashtags": []
},
{
    "rest_id": "1587781869365755904",
    "like_count": 9,
    "quote_count": 0,
    "reply_count": 1,
    "retweet_count": 1,
    "bookmark_count": 2,
    "content": "@officialavatar aaaah I\u2019m so excited! My uncle\u2019s credit card number is 4193 0048 2617 8277, 09/25, 614, 60611\n\nI would like to give James Cameron $57.62 as a token of my appreciation for creating such an amazing universe. I love avatar, the greatest movie of all time and I can\u2019t wait for the seq",
    "hashtags": []
},
{
    "rest_id": "1588092245810577410",
    "like_count": 0,
    "quote_count": 0,
    "reply_count": 0,
    "retweet_count": 0,
    "bookmark_count": 0,
    "content": "@officialavatar sadly the YT video isnt in 4k and the quality is abysmal at the start :( any chance we can download the trailer in good quality from somewhere?",
    "hashtags": []
},
{
    "rest_id": "1587783000900923392",
    "like_count": 0,
    "quote_count": 0,
    "reply_count": 0,
    "retweet_count": 0,
    "bookmark_count": 0,
    "content": "@officialavatar Avg raa",
    "hashtags": []
},
{
    "rest_id": "1587783695544770561",
    "like_count": 0,
    "quote_count": 0,
    "reply_count": 0,
    "retweet_count": 0,
    "bookmark_count": 0,
    "content": "@officialavatar Mesmerizing",
    "hashtags": []
},
{
    "rest_id": "1587786053762846720",
    "like_count": 0,
    "quote_count": 0,
    "reply_count": 0,
    "retweet_count": 0,
    "bookmark_count": 0,
    "content": "@officialavatar Where is the YouTube video link ?",
    "hashtags": []
},
{
    "rest_id": "1587782323428548608",
    "like_count": 48,
    "quote_count": 0,
    "reply_count": 10,
    "retweet_count": 10,
    "bookmark_count": 0,
    "content": "@officialavatar https://t.co/cMLjD6AXJW",
    "hashtags": []
},
{
    "rest_id": "1587790079463870465",
    "like_count": 173,
    "quote_count": 2,
    "reply_count": 17,
    "retweet_count": 3,
    "bookmark_count": 3,
    "content": "@officialavatar There\u2019s no way possible someone can watch this trailer and just say \u201cmeh\u201d",
    "hashtags": []
},
{
    "rest_id": "1587783159562780672",
    "like_count": 3,
    "quote_count": 0,
    "reply_count": 1,
    "retweet_count": 0,
    "bookmark_count": 0,
    "content": "@officialavatar @ShizzleREborn @CineRexo",
    "hashtags": []
},
{
    "rest_id": "1587781682643734530",
    "like_count": 4,
    "quote_count": 0,
    "reply_count": 0,
    "retweet_count": 1,
    "bookmark_count": 0,
    "content": "@officialavatar What a trailer frist to watch",
    "hashtags": []
},
{
    "rest_id": "1587782943606702083",
    "like_count": 104,
    "quote_count": 0,
    "reply_count": 4,
    "retweet_count": 19,
    "bookmark_count": 2,
    "content": "@officialavatar \u0c27\u0c4b\u0c28\u0c40 \u0c32\u0c47\u0c28\u0c3f \u0c32\u0c4b\u0c1f\u0c41 \u0c38\u0c4d\u0c2a\u0c37\u0c4d\u0c1f\u0c02\u0c17\u0c3e \u0c15\u0c28\u0c2a\u0c21\u0c41\u0c24\u0c41\u0c02\u0c26\u0c3f..\ud83d\ude25\ud83e\udd7a https://t.co/YIKKp0hVQ9",
    "hashtags": []
},
{
    "rest_id": "1587782488344010752",
    "like_count": 1,
    "quote_count": 0,
    "reply_count": 0,
    "retweet_count": 1,
    "bookmark_count": 0,
    "content": "@officialavatar Adhi atta",
    "hashtags": []
},
{
    "rest_id": "1587783361912717314",
    "like_count": 0,
    "quote_count": 0,
    "reply_count": 0,
    "retweet_count": 0,
    "bookmark_count": 0,
    "content": "@officialavatar Best wishes from @HailPrabhas007 Anna fans \u2763\ufe0f\u270c\ufe0f",
    "hashtags": []
},
{
    "rest_id": "1587862857001144321",
    "like_count": 0,
    "quote_count": 0,
    "reply_count": 0,
    "retweet_count": 0,
    "bookmark_count": 0,
    "content": "@officialavatar Crop your vids guys!",
    "hashtags": []
},
{
    "rest_id": "1587793288605548545",
    "like_count": 20,
    "quote_count": 0,
    "reply_count": 0,
    "retweet_count": 3,
    "bookmark_count": 0,
    "content": "@officialavatar JimCameron &amp; Team \nAll The Best From Darling #Prabhas Fans #AvatarTheWayOfWater https://t.co/fudcoRee0R",
    "hashtags": [
        {
            "indices": [
                65,
                73
            ],
            "text": "Prabhas"
        },
        {
            "indices": [
                79,
                99
            ],
            "text": "AvatarTheWayOfWater"
        }
    ]
},
{
    "rest_id": "1587783131507355648",
    "like_count": 4,
    "quote_count": 0,
    "reply_count": 1,
    "retweet_count": 0,
    "bookmark_count": 0,
    "content": "@officialavatar You tube lo upload chey bro quality ravtam le",
    "hashtags": []
},
{
    "rest_id": "1587782029256671232",
    "like_count": 5,
    "quote_count": 0,
    "reply_count": 0,
    "retweet_count": 0,
    "bookmark_count": 0,
    "content": "@officialavatar Kiri looks so beautiful and sounds so good! #AvatarTheWayOfWater",
    "hashtags": [
        {
            "indices": [
                60,
                80
            ],
            "text": "AvatarTheWayOfWater"
        }
    ]
},
{
    "rest_id": "1587784543012065283",
    "like_count": 3,
    "quote_count": 0,
    "reply_count": 1,
    "retweet_count": 0,
    "bookmark_count": 0,
    "content": "@officialavatar I. Cannot. WAIT",
    "hashtags": []
},
{
    "rest_id": "1587782488034021381",
    "like_count": 0,
    "quote_count": 0,
    "reply_count": 0,
    "retweet_count": 0,
    "bookmark_count": 0,
    "content": "@officialavatar \u2665\ufe0f\u2665\ufe0f\u2665\ufe0f\u2665\ufe0f\u2665\ufe0f\u2665\ufe0f\u2665\ufe0f\ud83d\udc51\ud83d\udc51\ud83d\udc51",
    "hashtags": []
},
{
    "rest_id": "1587785492149452802",
    "like_count": 0,
    "quote_count": 0,
    "reply_count": 0,
    "retweet_count": 0,
    "bookmark_count": 0,
    "content": "@officialavatar \u064a\u0639\u0646\u064a \u0645\u0627\u0628\u064a\u0648\u0635\u0644\u0646\u0627 \u0627\u0644\u0627 \u0628\u0639\u062f \u0631\u0627\u0633 \u0627\u0644\u0633\u0646\u0647 2023 !!\u061f",
    "hashtags": []
},
{
    "rest_id": "1587781539462463489",
    "like_count": 17,
    "quote_count": 0,
    "reply_count": 2,
    "retweet_count": 2,
    "bookmark_count": 0,
    "content": "@officialavatar #Varisu",
    "hashtags": [
        {
            "indices": [
                16,
                23
            ],
            "text": "Varisu"
        }
    ]
},
{
    "rest_id": "1587783075114913792",
    "like_count": 0,
    "quote_count": 0,
    "reply_count": 0,
    "retweet_count": 0,
    "bookmark_count": 0,
    "content": "@officialavatar Emotional \ud83d\ude2d wow killed",
    "hashtags": []
},
{
    "rest_id": "1587793760481677318",
    "like_count": 1,
    "quote_count": 0,
    "reply_count": 1,
    "retweet_count": 0,
    "bookmark_count": 0,
    "content": "@officialavatar @joojosantoos",
    "hashtags": []
},
{
    "rest_id": "1587782133044903937",
    "like_count": 0,
    "quote_count": 0,
    "reply_count": 1,
    "retweet_count": 0,
    "bookmark_count": 0,
    "content": "@officialavatar @shipinbot",
    "hashtags": []
},
{
    "rest_id": "1587786578214400002",
    "like_count": 0,
    "quote_count": 0,
    "reply_count": 0,
    "retweet_count": 0,
    "bookmark_count": 0,
    "content": "@officialavatar The Way of Toruk Makto.",
    "hashtags": []
},
{
    "rest_id": "1587781868908212225",
    "like_count": 0,
    "quote_count": 0,
    "reply_count": 0,
    "retweet_count": 0,
    "bookmark_count": 0,
    "content": "@officialavatar Finally \u2764\u2728",
    "hashtags": []
},
{
    "rest_id": "1587783212960743424",
    "like_count": 0,
    "quote_count": 0,
    "reply_count": 0,
    "retweet_count": 0,
    "bookmark_count": 0,
    "content": "@officialavatar Expecting worth on waiting \ud83d\udc4d",
    "hashtags": []
},
{
    "rest_id": "1587783547581911040",
    "like_count": 0,
    "quote_count": 0,
    "reply_count": 0,
    "retweet_count": 0,
    "bookmark_count": 0,
    "content": "@officialavatar match chustunte madyalo nee gola endira ungamma",
    "hashtags": []
},
{
    "rest_id": "1587807870514364418",
    "like_count": 1,
    "quote_count": 0,
    "reply_count": 0,
    "retweet_count": 1,
    "bookmark_count": 0,
    "content": "@Narendran_ @officialavatar Here's your screenshot.\n\n\u26a1 Want to automatically post your tweets on Instagram? Visit https://t.co/6fIpjtsiEr. https://t.co/kkMCvpSU7j",
    "hashtags": []
},
{
    "rest_id": "1587782670112677890",
    "like_count": 15,
    "quote_count": 0,
    "reply_count": 0,
    "retweet_count": 0,
    "bookmark_count": 0,
    "content": "@officialavatar Can't wait to see it opening weekend next month. Been such a long wait but it will be worth it https://t.co/WveEIjRFs6",
    "hashtags": []
},
{
    "rest_id": "1587817911133278209",
    "like_count": 0,
    "quote_count": 0,
    "reply_count": 0,
    "retweet_count": 0,
    "bookmark_count": 0,
    "content": "@officialavatar Trailer not to reach expectations",
    "hashtags": []
},
{
    "rest_id": "1587785504845504513",
    "like_count": 8,
    "quote_count": 0,
    "reply_count": 0,
    "retweet_count": 0,
    "bookmark_count": 0,
    "content": "@officialavatar Ginna aaa bokka feels\ud83e\udd73\ud83e\udd73 https://t.co/22kHpI7oHc",
    "hashtags": []
},
{
    "rest_id": "1587786183412977664",
    "like_count": 6,
    "quote_count": 0,
    "reply_count": 1,
    "retweet_count": 0,
    "bookmark_count": 0,
    "content": "@officialavatar Marvel Jaathini egaresi egaresi Dhenguthunnam \u2620\ud83e\udd75",
    "hashtags": []
},
{
    "rest_id": "1587782528697602048",
    "like_count": 1,
    "quote_count": 0,
    "reply_count": 0,
    "retweet_count": 0,
    "bookmark_count": 0,
    "content": "@officialavatar Awesome.",
    "hashtags": []
},
{
    "rest_id": "1587781572958113792",
    "like_count": 91,
    "quote_count": 0,
    "reply_count": 2,
    "retweet_count": 4,
    "bookmark_count": 0,
    "content": "@officialavatar Box-office 100B$ loading.....\ud83d\udd25\ud83d\udd25",
    "hashtags": []
},
{
    "rest_id": "1587782041495818241",
    "like_count": 255,
    "quote_count": 0,
    "reply_count": 0,
    "retweet_count": 3,
    "bookmark_count": 5,
    "content": "@officialavatar December going to be\u270c\ud83c\udffb https://t.co/2kzMmUKa85",
    "hashtags": []
},
{
    "rest_id": "1587783658890575873",
    "like_count": 0,
    "quote_count": 0,
    "reply_count": 1,
    "retweet_count": 0,
    "bookmark_count": 0,
    "content": "@officialavatar CGI looks a bit rough in places but I'm willing to keep an open mind until I see it in cinemas.",
    "hashtags": []
},
{
    "rest_id": "1587783444226256896",
    "like_count": 0,
    "quote_count": 0,
    "reply_count": 0,
    "retweet_count": 0,
    "bookmark_count": 0,
    "content": "@officialavatar \ud83d\udca5\ud83d\udc4c",
    "hashtags": []
},
{
    "rest_id": "1587783286654476288",
    "like_count": 0,
    "quote_count": 0,
    "reply_count": 0,
    "retweet_count": 0,
    "bookmark_count": 0,
    "content": "@officialavatar Epic !",
    "hashtags": []
},
{
    "rest_id": "1587781920863264769",
    "like_count": 3,
    "quote_count": 0,
    "reply_count": 1,
    "retweet_count": 0,
    "bookmark_count": 0,
    "content": "@officialavatar @RinoTheBouncer Cant wait \ud83d\ude0d https://t.co/3McMGOtih2",
    "hashtags": []
},
{
    "rest_id": "1587783892542464001",
    "like_count": 0,
    "quote_count": 0,
    "reply_count": 0,
    "retweet_count": 0,
    "bookmark_count": 0,
    "content": "@officialavatar \ud83d\udca5\ud83d\udca5\ud83d\udd25\ud83d\udd25",
    "hashtags": []
},
{
    "rest_id": "1590831719053418497",
    "like_count": 1,
    "quote_count": 0,
    "reply_count": 0,
    "retweet_count": 0,
    "bookmark_count": 0,
    "content": "@officialavatar Waiting for the day when existing as an avatar is possible? Sci-Fi became a reality this weekend as the Avatar XPRIZE took one giant leap with human telepresence. Learn more about the innovators behind the future of avatar technology: https://t.co/2WzjF3Fi5z #AvatarXPRIZE",
    "hashtags": [
        {
            "indices": [
                275,
                288
            ],
            "text": "AvatarXPRIZE"
        }
    ]
},
{
    "rest_id": "1587785214612410370",
    "like_count": 1,
    "quote_count": 0,
    "reply_count": 0,
    "retweet_count": 0,
    "bookmark_count": 0,
    "content": "@officialavatar Tickets on sale yet? I need to get my IMAX tickets",
    "hashtags": []
},
{
    "rest_id": "1587786674603294720",
    "like_count": 1,
    "quote_count": 0,
    "reply_count": 0,
    "retweet_count": 0,
    "bookmark_count": 0,
    "content": "@officialavatar Weird choice to go all live action and no CGI for the sequel. Bold.",
    "hashtags": []
},
{
    "rest_id": "1587795222150500352",
    "like_count": 1,
    "quote_count": 0,
    "reply_count": 1,
    "retweet_count": 0,
    "bookmark_count": 0,
    "content": "@officialavatar @engineer_ndulka hona visuals",
    "hashtags": []
},
{
    "rest_id": "1587782019018559488",
    "like_count": 2,
    "quote_count": 0,
    "reply_count": 0,
    "retweet_count": 0,
    "bookmark_count": 0,
    "content": "@officialavatar Incredible \ud83c\udf0a",
    "hashtags": []
},
{
    "rest_id": "1587783033369022464",
    "like_count": 0,
    "quote_count": 0,
    "reply_count": 0,
    "retweet_count": 0,
    "bookmark_count": 0,
    "content": "@officialavatar pretty average ...",
    "hashtags": []
},
{
    "rest_id": "1587782448263598080",
    "like_count": 1,
    "quote_count": 0,
    "reply_count": 0,
    "retweet_count": 1,
    "bookmark_count": 0,
    "content": "@officialavatar \u2764\ufe0f\u200d\ud83d\udd25",
    "hashtags": []
},
{
    "rest_id": "1587781665740718081",
    "like_count": 0,
    "quote_count": 0,
    "reply_count": 1,
    "retweet_count": 0,
    "bookmark_count": 0,
    "content": "@officialavatar Kingu kingu",
    "hashtags": []
},
{
    "rest_id": "1587789202904993792",
    "like_count": 37,
    "quote_count": 0,
    "reply_count": 3,
    "retweet_count": 2,
    "bookmark_count": 1,
    "content": "@officialavatar In honour of the trailer releasing, I wanted to share an art piece by a good mate, Tapion. Here\u2019s his piece on Tonowari from #AvatarTheWayOfWater \n@JimCameron @jonlandau #AlitaArmy",
    "hashtags": [
        {
            "indices": [
                141,
                161
            ],
            "text": "AvatarTheWayOfWater"
        },
        {
            "indices": [
                186,
                196
            ],
            "text": "AlitaArmy"
        }
    ]
},
{
    "rest_id": "1587781932485869569",
    "like_count": 5,
    "quote_count": 0,
    "reply_count": 1,
    "retweet_count": 0,
    "bookmark_count": 0,
    "content": "@officialavatar Wow this is called teaser n uniquness",
    "hashtags": []
},
{
    "rest_id": "1587785898263040001",
    "like_count": 1,
    "quote_count": 0,
    "reply_count": 0,
    "retweet_count": 0,
    "bookmark_count": 0,
    "content": "@officialavatar OMG there are No Words!!! \ud83d\ude0d\ud83d\ude0d\ud83d\ude0d",
    "hashtags": []
},
{
    "rest_id": "1587787561933864962",
    "like_count": 0,
    "quote_count": 0,
    "reply_count": 0,
    "retweet_count": 0,
    "bookmark_count": 0,
    "content": "@officialavatar \ud83d\udd25\ud83d\udca5",
    "hashtags": []
},
{
    "rest_id": "1587783309182251009",
    "like_count": 0,
    "quote_count": 0,
    "reply_count": 0,
    "retweet_count": 0,
    "bookmark_count": 0,
    "content": "@officialavatar \ud83d\ude0d\ud83d\ude0d\ud83d\ude0d",
    "hashtags": []
},
{
    "rest_id": "1587783702482128897",
    "like_count": 0,
    "quote_count": 0,
    "reply_count": 0,
    "retweet_count": 0,
    "bookmark_count": 0,
    "content": "@officialavatar Waiting \ud83d\udd25\ud83d\udd25\ud83d\udd25\ud83d\udd25\ud83d\udd25",
    "hashtags": []
},
{
    "rest_id": "1587785932698263553",
    "like_count": 3,
    "quote_count": 0,
    "reply_count": 0,
    "retweet_count": 0,
    "bookmark_count": 0,
    "content": "@officialavatar Cinema",
    "hashtags": []
},
{
    "rest_id": "1587781469191036928",
    "like_count": 94033,
    "quote_count": 8511,
    "reply_count": 1665,
    "retweet_count": 26770,
    "bookmark_count": 1417,
    "content": "On December 16, return to Pandora.\n\nWatch the brand-new trailer and experience #AvatarTheWayOfWater in 3D. https://t.co/UtxAbycCIc",
    "hashtags": [
        {
            "indices": [
                79,
                99
            ],
            "text": "AvatarTheWayOfWater"
        }
    ]
},
{
    "rest_id": "1587782338955673602",
    "like_count": 0,
    "quote_count": 0,
    "reply_count": 0,
    "retweet_count": 0,
    "bookmark_count": 0,
    "content": "@officialavatar dude.... this is beautiful...",
    "hashtags": []
},
{
    "rest_id": "1587783770081726464",
    "like_count": 0,
    "quote_count": 0,
    "reply_count": 0,
    "retweet_count": 0,
    "bookmark_count": 0,
    "content": "@officialavatar Enthaina #Ginna collections ni beat cheyadam kastam James Cameron garu\ud83e\udd71",
    "hashtags": [
        {
            "indices": [
                25,
                31
            ],
            "text": "Ginna"
        }
    ]
},
{
    "rest_id": "1587781880686039040",
    "like_count": 7,
    "quote_count": 0,
    "reply_count": 1,
    "retweet_count": 0,
    "bookmark_count": 0,
    "content": "@officialavatar https://t.co/F4YCGvb5vF",
    "hashtags": []
},
{
    "rest_id": "1587782679172349954",
    "like_count": 10,
    "quote_count": 0,
    "reply_count": 1,
    "retweet_count": 0,
    "bookmark_count": 0,
    "content": "@officialavatar Made for the big big screen.",
    "hashtags": []
},
{
    "rest_id": "1587783606684250113",
    "like_count": 0,
    "quote_count": 0,
    "reply_count": 1,
    "retweet_count": 0,
    "bookmark_count": 0,
    "content": "@officialavatar This is actually flawless",
    "hashtags": []
},
{
    "rest_id": "1587783198502957057",
    "like_count": 0,
    "quote_count": 0,
    "reply_count": 0,
    "retweet_count": 0,
    "bookmark_count": 0,
    "content": "@officialavatar YouTube ?",
    "hashtags": []
},
{
    "rest_id": "1588041787826130944",
    "like_count": 1,
    "quote_count": 0,
    "reply_count": 0,
    "retweet_count": 0,
    "bookmark_count": 0,
    "content": "@officialavatar #Avatar2InKannada \nAny reason why there is no kannada version?",
    "hashtags": [
        {
            "indices": [
                16,
                33
            ],
            "text": "Avatar2InKannada"
        }
    ]
},
{
    "rest_id": "1587787758869053442",
    "like_count": 8,
    "quote_count": 0,
    "reply_count": 0,
    "retweet_count": 3,
    "bookmark_count": 0,
    "content": "@officialavatar Can't wait!! #AvatarTheWayOfWater https://t.co/4d1qxSFjRd",
    "hashtags": [
        {
            "indices": [
                29,
                49
            ],
            "text": "AvatarTheWayOfWater"
        }
    ]
},
{
    "rest_id": "1587783785587916800",
    "like_count": 0,
    "quote_count": 0,
    "reply_count": 0,
    "retweet_count": 0,
    "bookmark_count": 0,
    "content": "@officialavatar Finally! \u2764\ufe0f",
    "hashtags": []
},
{
    "rest_id": "1587786676318896129",
    "like_count": 160,
    "quote_count": 0,
    "reply_count": 4,
    "retweet_count": 3,
    "bookmark_count": 3,
    "content": "@officialavatar \ud83e\udd79\ud83e\udd79\ud83e\udd79\ud83d\udc76 https://t.co/YSRYqZx0aR",
    "hashtags": []
},
{
    "rest_id": "1587783033205456897",
    "like_count": 0,
    "quote_count": 0,
    "reply_count": 0,
    "retweet_count": 0,
    "bookmark_count": 0,
    "content": "@officialavatar \ud83d\udd25\ud83d\udd25\ud83d\udd25\ud83d\udd25\ud83d\udd25\ud83d\udca5\ud83d\udca5",
    "hashtags": []
},
{
    "rest_id": "1587786164081405953",
    "like_count": 2,
    "quote_count": 0,
    "reply_count": 0,
    "retweet_count": 0,
    "bookmark_count": 0,
    "content": "@officialavatar @SomuKOffl Iam waiting for the movie",
    "hashtags": []
},
{
    "rest_id": "1587782355900858368",
    "like_count": 0,
    "quote_count": 0,
    "reply_count": 0,
    "retweet_count": 0,
    "bookmark_count": 0,
    "content": "@officialavatar \ud83d\udd25",
    "hashtags": []
},
{
    "rest_id": "1587796861188210690",
    "like_count": 7,
    "quote_count": 0,
    "reply_count": 0,
    "retweet_count": 0,
    "bookmark_count": 0,
    "content": "@officialavatar Can\u2019t believe that after so many years we\u2019re finally gonna be able to see this masterpiece sequel!!! \ud83d\ude2d\ud83d\ude2d\ud83d\ude2d",
    "hashtags": []
},
{
    "rest_id": "1587785102397931521",
    "like_count": 10,
    "quote_count": 0,
    "reply_count": 0,
    "retweet_count": 0,
    "bookmark_count": 0,
    "content": "@officialavatar Experience the magic of cinema like never before \ud83d\udca5\ud83d\udca5\ud83d\udca5\ud83d\udca5\ud83d\udca5 #Avatar #AvatarTheWayOfWater https://t.co/TgbPQJtNDo",
    "hashtags": [
        {
            "indices": [
                71,
                78
            ],
            "text": "Avatar"
        },
        {
            "indices": [
                79,
                99
            ],
            "text": "AvatarTheWayOfWater"
        }
    ]
},
{
    "rest_id": "1587784220227014656",
    "like_count": 0,
    "quote_count": 0,
    "reply_count": 0,
    "retweet_count": 0,
    "bookmark_count": 0,
    "content": "@officialavatar This looks like CGI from 1998.",
    "hashtags": []
},
{
    "rest_id": "1587782589548728321",
    "like_count": 2,
    "quote_count": 0,
    "reply_count": 0,
    "retweet_count": 0,
    "bookmark_count": 0,
    "content": "@officialavatar waiting \ud83d\ude3b Tamil dubbed in December 16",
    "hashtags": []
},
{
    "rest_id": "1587810686679277568",
    "like_count": 20,
    "quote_count": 0,
    "reply_count": 0,
    "retweet_count": 0,
    "bookmark_count": 0,
    "content": "@officialavatar Can\u2019t wait to wash this in IMAX the day it drops",
    "hashtags": []
},
{
    "rest_id": "1587786624926195712",
    "like_count": 21,
    "quote_count": 0,
    "reply_count": 0,
    "retweet_count": 2,
    "bookmark_count": 0,
    "content": "@officialavatar Best wishes to the team from #Prabhas fans \ud83d\udd25\nSoo excited to watch \n\n#AvatarTheWayOfWater https://t.co/1DVtM59i5S",
    "hashtags": [
        {
            "indices": [
                45,
                53
            ],
            "text": "Prabhas"
        },
        {
            "indices": [
                84,
                104
            ],
            "text": "AvatarTheWayOfWater"
        }
    ]
},
{
    "rest_id": "1587784431531696129",
    "like_count": 23,
    "quote_count": 0,
    "reply_count": 0,
    "retweet_count": 1,
    "bookmark_count": 0,
    "content": "@officialavatar Looks wow!!!! 500CR+ INR @ Indian Boxoffice a huge possiblity \ud83d\udca5 #AvatarTheWayOfWater Dec 16, 2022 release. https://t.co/g9X7EMdqYy",
    "hashtags": [
        {
            "indices": [
                80,
                100
            ],
            "text": "AvatarTheWayOfWater"
        }
    ]
},
{
    "rest_id": "1587784104489148418",
    "like_count": 34,
    "quote_count": 0,
    "reply_count": 0,
    "retweet_count": 1,
    "bookmark_count": 0,
    "content": "@officialavatar It'll be worth all these years of wait. Just a little longer and I feel like it'll be spectacular and unforgettable experience again. \u2764 https://t.co/CUXHzbPe8J",
    "hashtags": []
},
{
    "rest_id": "1587783473582018561",
    "like_count": 0,
    "quote_count": 0,
    "reply_count": 0,
    "retweet_count": 0,
    "bookmark_count": 0,
    "content": "@officialavatar I'm not crying I just have some tears in my eyes!!!",
    "hashtags": []
},
{
    "rest_id": "1587782070822051840",
    "like_count": 4,
    "quote_count": 0,
    "reply_count": 0,
    "retweet_count": 0,
    "bookmark_count": 0,
    "content": "@officialavatar What a timing mawa",
    "hashtags": []
},
{
    "rest_id": "1587786796653592577",
    "like_count": 2,
    "quote_count": 0,
    "reply_count": 2,
    "retweet_count": 0,
    "bookmark_count": 0,
    "content": "@officialavatar https://t.co/iaTlVPPnlW",
    "hashtags": []
},
{
    "rest_id": "1587784522699255808",
    "like_count": 1,
    "quote_count": 0,
    "reply_count": 1,
    "retweet_count": 0,
    "bookmark_count": 0,
    "content": "@officialavatar avengers &gt;&gt;&gt;&gt; avatar",
    "hashtags": []
},
{
    "rest_id": "1587784514092535808",
    "like_count": 1,
    "quote_count": 0,
    "reply_count": 0,
    "retweet_count": 0,
    "bookmark_count": 0,
    "content": "@officialavatar @YouTubeIndia @YouTube ?? @20thcentury !!",
    "hashtags": []
},
{
    "rest_id": "1587785816751099904",
    "like_count": 1,
    "quote_count": 0,
    "reply_count": 0,
    "retweet_count": 0,
    "bookmark_count": 0,
    "content": "@officialavatar https://t.co/1pjE4GJ8C8",
    "hashtags": []
},
{
    "rest_id": "1587789059984064514",
    "like_count": 1,
    "quote_count": 0,
    "reply_count": 2,
    "retweet_count": 0,
    "bookmark_count": 0,
    "content": "@officialavatar @Chaitanyaackr book ticket",
    "hashtags": []
},
{
    "rest_id": "1587804473665388550",
    "like_count": 9,
    "quote_count": 0,
    "reply_count": 0,
    "retweet_count": 2,
    "bookmark_count": 0,
    "content": "@officialavatar #Prabhas https://t.co/3E4hIcfxtg",
    "hashtags": [
        {
            "indices": [
                16,
                24
            ],
            "text": "Prabhas"
        }
    ]
},
{
    "rest_id": "1587784589057363968",
    "like_count": 154,
    "quote_count": 1,
    "reply_count": 2,
    "retweet_count": 11,
    "bookmark_count": 0,
    "content": "@officialavatar Thirteen years of waiting for the feast nd finally December 16th nearing \ud83d\ude0d\ud83d\ude0d\n\nAn absolute visual wonder \ud83d\udd25\ud83d\udd25\n\n#AvatarTheWayOfWater https://t.co/uUBC6nVA4a",
    "hashtags": [
        {
            "indices": [
                123,
                143
            ],
            "text": "AvatarTheWayOfWater"
        }
    ]
},
{
    "rest_id": "1587782671077605376",
    "like_count": 2,
    "quote_count": 0,
    "reply_count": 0,
    "retweet_count": 0,
    "bookmark_count": 0,
    "content": "@officialavatar Telugu states 100cr  loading \ud83d\ude0e\ud83d\ude0e",
    "hashtags": []
},
{
    "rest_id": "1587785756453412864",
    "like_count": 2,
    "quote_count": 0,
    "reply_count": 0,
    "retweet_count": 0,
    "bookmark_count": 0,
    "content": "@officialavatar Trailer which takes us into the new world of Pandora \ud83d\ude0d\ud83d\udc4c\ud83c\udffd \n\nHope to see another trailer revealing the antagonists. Looking forward \ud83d\ude0d\ud83d\udd25",
    "hashtags": []
},
{
    "rest_id": "1587814538774052864",
    "like_count": 7,
    "quote_count": 0,
    "reply_count": 2,
    "retweet_count": 2,
    "bookmark_count": 1,
    "content": "@officialavatar I write the truth and only the truth:\nhttps://t.co/CeVXRELV6J",
    "hashtags": []
},
{
    "rest_id": "1587798697592918016",
    "like_count": 0,
    "quote_count": 0,
    "reply_count": 0,
    "retweet_count": 0,
    "bookmark_count": 0,
    "content": "@officialavatar irayo!!",
    "hashtags": []
},
{
    "rest_id": "1587781917336014849",
    "like_count": 0,
    "quote_count": 0,
    "reply_count": 0,
    "retweet_count": 0,
    "bookmark_count": 0,
    "content": "@officialavatar CAN'T WAIT!",
    "hashtags": []
},
{
    "rest_id": "1587921825090396160",
    "like_count": 0,
    "quote_count": 0,
    "reply_count": 1,
    "retweet_count": 0,
    "bookmark_count": 0,
    "content": "@officialavatar @Parletalk \ud83d\udd25 \ud83d\udd25 \ud83d\udd25",
    "hashtags": []
},
{
    "rest_id": "1587783376572157952",
    "like_count": 0,
    "quote_count": 0,
    "reply_count": 0,
    "retweet_count": 0,
    "bookmark_count": 0,
    "content": "@officialavatar cringe",
    "hashtags": []
},
{
    "rest_id": "1587799711880466433",
    "like_count": 3,
    "quote_count": 0,
    "reply_count": 0,
    "retweet_count": 0,
    "bookmark_count": 0,
    "content": "@officialavatar Kcpd ye records motham worldwide https://t.co/sVsATLzgpB",
    "hashtags": []
},
{
    "rest_id": "1587782423609229315",
    "like_count": 58,
    "quote_count": 0,
    "reply_count": 2,
    "retweet_count": 1,
    "bookmark_count": 0,
    "content": "@officialavatar I can\u2019t wait to see this in HFR 3D!\ud83d\ude0e\ud83c\udf0c The Baby Avatars looks so adorable! https://t.co/HTOY553K1w",
    "hashtags": []
},
{
    "rest_id": "1587782822370377728",
    "like_count": 1,
    "quote_count": 0,
    "reply_count": 1,
    "retweet_count": 0,
    "bookmark_count": 0,
    "content": "@officialavatar @shainacamillee",
    "hashtags": []
},
{
    "rest_id": "1587783142525792257",
    "like_count": 2,
    "quote_count": 0,
    "reply_count": 0,
    "retweet_count": 0,
    "bookmark_count": 0,
    "content": "@officialavatar Andaru potharu\ud83e\udd75\n\nBo ni dunni para den\ud83e\udd41\n@JimCameron \ud83d\uded0",
    "hashtags": []
},
{
    "rest_id": "1587783426827964417",
    "like_count": 0,
    "quote_count": 0,
    "reply_count": 1,
    "retweet_count": 0,
    "bookmark_count": 0,
    "content": "@officialavatar Star wars domestic lechuddi",
    "hashtags": []
},
{
    "rest_id": "1587791842027995138",
    "like_count": 1,
    "quote_count": 0,
    "reply_count": 2,
    "retweet_count": 0,
    "bookmark_count": 0,
    "content": "@officialavatar Until I'm sat in the cinema and this films logo appears on the screen there's absolutely no way I believe this is actually coming out after the past 10 years \ud83d\ude02\ud83d\ude02\ud83d\ude02",
    "hashtags": []
},
{
    "rest_id": "1587819196636753920",
    "like_count": 3,
    "quote_count": 0,
    "reply_count": 0,
    "retweet_count": 0,
    "bookmark_count": 0,
    "content": "@officialavatar Absolutely stunning \ud83d\udc99",
    "hashtags": []
},
{
    "rest_id": "1587784080040435713",
    "like_count": 2,
    "quote_count": 0,
    "reply_count": 0,
    "retweet_count": 0,
    "bookmark_count": 0,
    "content": "@officialavatar One of the best ever making in the history of world cinema\n\n#AvatarTheWayOfWater #Avatar2Trailer #Varisu",
    "hashtags": [
        {
            "indices": [
                76,
                96
            ],
            "text": "AvatarTheWayOfWater"
        },
        {
            "indices": [
                97,
                112
            ],
            "text": "Avatar2Trailer"
        },
        {
            "indices": [
                113,
                120
            ],
            "text": "Varisu"
        }
    ]
},
{
    "rest_id": "1587781991814303745",
    "like_count": 0,
    "quote_count": 0,
    "reply_count": 0,
    "retweet_count": 0,
    "bookmark_count": 0,
    "content": "@officialavatar BROOO",
    "hashtags": []
},
{
    "rest_id": "1587783315922173954",
    "like_count": 1664,
    "quote_count": 6,
    "reply_count": 6,
    "retweet_count": 157,
    "bookmark_count": 16,
    "content": "@officialavatar Me watching avatar 1 vs me now watching avatar 2 \ud83d\ude0e\ud83d\ude0e https://t.co/L3ApuBpNAt",
    "hashtags": []
},
{
    "rest_id": "1587789141525336067",
    "like_count": 1,
    "quote_count": 0,
    "reply_count": 0,
    "retweet_count": 1,
    "bookmark_count": 0,
    "content": "@officialavatar #WaltairVeeraya",
    "hashtags": [
        {
            "indices": [
                16,
                31
            ],
            "text": "WaltairVeeraya"
        }
    ]
},
{
    "rest_id": "1587781666613121024",
    "like_count": 6,
    "quote_count": 0,
    "reply_count": 0,
    "retweet_count": 0,
    "bookmark_count": 0,
    "content": "@officialavatar #Salaar tag mathram spam cheyakandi ra \ud83e\udd23\ud83e\udd23",
    "hashtags": [
        {
            "indices": [
                16,
                23
            ],
            "text": "Salaar"
        }
    ]
},
